processamento-imagem-desafioDIO/__init__.py
processamento-imagem-desafioDIO/executar/__init__.py
processamento-imagem-desafioDIO/executar/entrada-saida.py
processamento-imagem-desafioDIO/executar/entradasaida.py
processamento-imagem-desafioDIO/executar/plotar.py
processamento-imagem-desafioDIO/processamento/__init__.py
processamento-imagem-desafioDIO/processamento/combinar.py
processamento-imagem-desafioDIO/processamento/transformar.py
processamento_imagem_desafioDIO/__init__.py
processamento_imagem_desafioDIO/executar/__init__.py
processamento_imagem_desafioDIO/executar/entradasaida.py
processamento_imagem_desafioDIO/executar/plotar.py
processamento_imagem_desafioDIO/processamento/__init__.py
processamento_imagem_desafioDIO/processamento/combinar.py
processamento_imagem_desafioDIO/processamento/transformar.py
processamento_imagem_desafioDIO-0.0.4.dist-info/METADATA
processamento_imagem_desafioDIO-0.0.4.dist-info/WHEEL
processamento_imagem_desafioDIO-0.0.4.dist-info/top_level.txt
processamento_imagem_desafioDIO-0.0.4.dist-info/RECORD
