Metadata-Version: 2.1
Name: processamento-imagem-desafioDIO
Version: 0.0.4
Summary: Pacote para processamento de imagens.
Home-page: https://github.com/rafaelbmorais/processamento-de-imagem-python
Author: Rafael Morais
Author-email: ra.fa.morais@hotmail.com
License: UNKNOWN
Platform: UNKNOWN
Requires-Python: >=3.8
Requires-Dist: matplotlib
Requires-Dist: numpy
Requires-Dist: scikit-image
